mrrobot/__init__.py
mrrobot/__main__.py
mrrobot/app/__init__.py
mrrobot/app/arguments.py
mrrobot/app/configuration.py
mrrobot/app/display.py
mrrobot/app/exception.py
mrrobot/app/units.py
mrrobot/units/__init__.py
mrrobot/units/crypto/__init__.py
mrrobot/units/crypto/a1z26.py
mrrobot/units/crypto/a1z27.py
mrrobot/units/crypto/base64.py
mrrobot/units/crypto/caesar.py
mrrobot/units/crypto/geocountry.py
mrrobot/units/crypto/reverse.py
mrrobot/units/crypto/whitespace.py
mrrobot/units/esoteric/__init__.py
mrrobot/units/esoteric/brainfuck.py
mrrobot/units/esoteric/ook.py
mrrobot/units/forensics/__init__.py
mrrobot/units/forensics/lsb.py
mrrobot/units/forensics/strings.py
mrrobot-1.0.3.dist-info/LICENSE
mrrobot-1.0.3.dist-info/METADATA
mrrobot-1.0.3.dist-info/WHEEL
mrrobot-1.0.3.dist-info/entry_points.txt
mrrobot-1.0.3.dist-info/top_level.txt
mrrobot-1.0.3.dist-info/zip-safe
mrrobot-1.0.3.dist-info/RECORD
